LICENSE
MANIFEST.in
README.md
setup.py
gknames/__init__.py
gknames/__version__.py
gknames/generate_mod_wsgi_apachectl.sh
gknames/manage.py
gknames.egg-info/PKG-INFO
gknames.egg-info/not-zip-safe
gknames/nameserver/__init__.py
gknames/nameserver/asgi.py
gknames/nameserver/models.py
gknames/nameserver/settings.py
gknames/nameserver/urls.py
gknames/nameserver/views.py
gknames/nameserver/wsgi.py
gknames/nameserver/templates/base_bootstrap.html
gknames/nameserver/templates/events.html
gknames/nameserver/templates/events_old.html
gknames/nameserverapi/__init__.py
gknames/nameserverapi/admin.py
gknames/nameserverapi/apps.py
gknames/nameserverapi/serializers.py
gknames/nameserverapi/tests.py
gknames/nameserverapi/urls.py
gknames/nameserverapi/views.py
gknames/nameserverapi/panstarrs/generateJSON.py
gknames/nameserverapi/panstarrs/import_all_nameserver_data.sh
gknames/schema/2008.sql
gknames/schema/2009.sql
gknames/schema/2010.sql
gknames/schema/2011.sql
gknames/schema/2012.sql
gknames/schema/2013.sql
gknames/schema/2014.sql
gknames/schema/2015.sql
gknames/schema/2016.sql
gknames/schema/2017.sql
gknames/schema/2018.sql
gknames/schema/2019.sql
gknames/schema/2020.sql
gknames/schema/2021.sql
gknames/schema/2022.sql
gknames/schema/2023.sql
gknames/schema/2024.sql
gknames/schema/2025.sql
gknames/schema/2026.sql
gknames/schema/2027.sql
gknames/schema/2028.sql
gknames/schema/2029.sql
gknames/schema/2030.sql
gknames/schema/akas.sql
gknames/schema/create_schema.sql
gknames/schema/events.sql
gknames/schema/update_schema_20240109.sql
gknames/staticfiles/css/main_bootstrap.css
gknames/staticfiles/images/qub_white_stacked_logo.png
gknames/utils/tsvToJSONCurl.py