Metadata-Version: 2.1
Name: gknames
Version: 0.0.9
Summary: Pan-STARRS and ATLAS name server.
Home-page: https://github.com/genghisken/gknames
Author: genghisken
Author-email: ken.w.smith@gmail.com
License: MIT
Classifier: Development Status :: 4 - Beta
Classifier: License :: OSI Approved :: MIT License
Classifier: Programming Language :: Python :: 3.6
Classifier: Topic :: Utilities
Requires-Python: >=3.6
License-File: LICENSE
